pymacaron_docker
