Metadata-Version: 2.1
Name: pymacaron-docker
Version: 0.0.50
Summary: Package a PyMacaron microservice into a Docker image
Home-page: https://github.com/pymacaron/pymacaron-docker
Author: Erwan Lemonnier
Author-email: erwan@lemonnier.se
License: BSD
Platform: any
Classifier: Environment :: Web Environment
Classifier: Intended Audience :: Developers
Classifier: License :: OSI Approved :: BSD License
Classifier: Operating System :: OS Independent
Classifier: Programming Language :: Python
Classifier: Topic :: Internet :: WWW/HTTP :: Dynamic Content
Classifier: Topic :: Software Development :: Libraries :: Python Modules
